{
  "id": "chacra-4-cardiaco-pratica-01",
  "categoria": "chakra_pratica",
  "chacra": "Cardíaco (Anahata)",
  "chacra_numero": 4,
  "tipo_pratica": "cristal",
  "nome_pratica": "Quartzo Rosa no peito",
  "como_aplicar": "Deite-se com um quartzo rosa sobre o coração por 10 minutos ao final do dia; respire a cor rosa.",
  "texto": "Quartzo Rosa no peito: Deite-se com um quartzo rosa sobre o coração por 10 minutos ao final do dia; respire a cor rosa.",
  "grounding": {
    "research_mtc_linha": 91,
    "research_mtc_secao": "§2 Cristais por Chácra",
    "research_mtc_file": ".hermes/plans/research-medicina-tradicional-2026-06-23.md",
    "open_source_url": "https://pt.wikipedia.org/wiki/Chakra"
  },
  "alucinacao_score": 0.9,
  "requires_professional_review": false
}
